odoo/addons/purchase_order_product_recommendation_brand/README.rst
odoo/addons/purchase_order_product_recommendation_brand/__init__.py
odoo/addons/purchase_order_product_recommendation_brand/__manifest__.py
odoo/addons/purchase_order_product_recommendation_brand/i18n/es.po
odoo/addons/purchase_order_product_recommendation_brand/i18n/purchase_order_product_recommendation_brand.pot
odoo/addons/purchase_order_product_recommendation_brand/readme/CONTRIBUTORS.rst
odoo/addons/purchase_order_product_recommendation_brand/readme/DESCRIPTION.rst
odoo/addons/purchase_order_product_recommendation_brand/readme/ROADMAP.rst
odoo/addons/purchase_order_product_recommendation_brand/readme/USAGE.rst
odoo/addons/purchase_order_product_recommendation_brand/static/description/icon.png
odoo/addons/purchase_order_product_recommendation_brand/static/description/index.html
odoo/addons/purchase_order_product_recommendation_brand/tests/__init__.py
odoo/addons/purchase_order_product_recommendation_brand/tests/test_recommendation.py
odoo/addons/purchase_order_product_recommendation_brand/wizards/__init__.py
odoo/addons/purchase_order_product_recommendation_brand/wizards/purchase_order_recommendation.py
odoo/addons/purchase_order_product_recommendation_brand/wizards/purchase_order_recommendation_view.xml
odoo13_addon_purchase_order_product_recommendation_brand-13.0.1.0.1.dist-info/METADATA
odoo13_addon_purchase_order_product_recommendation_brand-13.0.1.0.1.dist-info/WHEEL
odoo13_addon_purchase_order_product_recommendation_brand-13.0.1.0.1.dist-info/top_level.txt
odoo13_addon_purchase_order_product_recommendation_brand-13.0.1.0.1.dist-info/RECORD
